python_starters/__init__.py
python_starters/__main__.py
python_starters/py.typed
python_starters/starters_api.py
python_starters/starters_cli.py
python_starters-0.0.2.dist-info/LICENSE
python_starters-0.0.2.dist-info/METADATA
python_starters-0.0.2.dist-info/WHEEL
python_starters-0.0.2.dist-info/entry_points.txt
python_starters-0.0.2.dist-info/RECORD
