Metadata-Version: 2.1
Name: python-starters
Version: 0.0.2
Summary: Python Starters
Home-page: https://github.com/piskunow/python-starters
License: MIT
Author: Pablo Piskunow
Author-email: starters@piskunow.com
Requires-Python: >=3.11,<4.0
Classifier: Development Status :: 1 - Planning
Classifier: License :: OSI Approved :: MIT License
Classifier: Programming Language :: Python :: 3
Classifier: Programming Language :: Python :: 3.11
Classifier: Programming Language :: Python :: 3.12
Requires-Dist: certifi (>=2022.12.07)
Requires-Dist: click (>=8.0.1)
Requires-Dist: markdown-it-py (>=2.2.0)
Requires-Dist: mypy-extensions (>=1.0.0)
Requires-Dist: pre-commit-hooks (>=4.5)
Requires-Dist: pygments (>=2.15)
Requires-Dist: safety (>=2.2.0)
Requires-Dist: tornado (>=6.3.3)
Requires-Dist: typing-extensions (>=4.8)
Requires-Dist: urllib3 (>=1.26.18)
Project-URL: Changelog, https://github.com/piskunow/python-starters/releases
Project-URL: Documentation, https://python-starters.readthedocs.io
Project-URL: Repository, https://github.com/piskunow/python-starters
